{
  "kind": "coverage_report",
  "version": "1.0",
  "generatedAt": "2026-02-13T08:00:46.906Z",
  "sources": {
    "buildRequest": true,
    "implementationPlan": true
  },
  "requirements": {
    "total": 1,
    "implemented": 1,
    "items": [
      {
        "id": "REQ-1",
        "summary": "Update the existing CO₂ chart so the 'CO2 Right (%)' series is rendered in a lighter green than the 'CO2 Left (%)' series, and ensure the legend swatch matches those same colors.",
        "status": "implemented",
        "plannedFiles": [
          "frontend/src/components/CO2Chart.tsx",
          "frontend/src/index.css"
        ],
        "matchedFiles": [
          "frontend/src/index.css"
        ]
      }
    ]
  },
  "changedFiles": [
    "build-request.json",
    "feature_evidence.json",
    "frontend-file-summaries.txt",
    "frontend-implementation-plan.json",
    "frontend/src/index.css",
    "project_state.json",
    "scratch/component-selection.json",
    "spec.md",
    "spec_vs_diff_report.json"
  ]
}